[
  {
    "@class": "com.eptisa.dto.StationWaterLevelAboveWarningDto",
    "id": 1,
    "stationCode": "022-mgd4ptn",
    "status": "WARNING",
    "trend": null,
    "value": 74.28
  },
  {
    "@class": "com.eptisa.dto.StationWaterLevelAboveWarningDto",
    "id": 2,
    "stationCode": "011-UBDDIB",
    "status": "WARNING",
    "trend": null,
    "value": 134.3
  },
  {
    "@class": "com.eptisa.dto.StationWaterLevelAboveWarningDto",
    "id": 3,
    "stationCode": "013-UBDDIB",
    "status": "WARNING",
    "trend": null,
    "value": 101.25
  }
]