{
  "generated": 1775856363,
  "host": "https://tilecache.rainviewer.com",
  "radar": {
    "past": [
      {
        "time": 1775848800,
        "path": "/v2/radar/1ada31adb00d"
      },
      {
        "time": 1775849400,
        "path": "/v2/radar/b6c172ec6360"
      },
      {
        "time": 1775850000,
        "path": "/v2/radar/403e9ccb06d6"
      },
      {
        "time": 1775850600,
        "path": "/v2/radar/d00935c88af2"
      },
      {
        "time": 1775851200,
        "path": "/v2/radar/0a5bb9f10134"
      },
      {
        "time": 1775851800,
        "path": "/v2/radar/f5def6f203af"
      },
      {
        "time": 1775852400,
        "path": "/v2/radar/dc71c976ae08"
      },
      {
        "time": 1775853000,
        "path": "/v2/radar/d0d034b9d7f4"
      },
      {
        "time": 1775853600,
        "path": "/v2/radar/46baa6d64f9c"
      },
      {
        "time": 1775854200,
        "path": "/v2/radar/8c7c57e85c5e"
      },
      {
        "time": 1775854800,
        "path": "/v2/radar/e331af2ee6a4"
      },
      {
        "time": 1775855400,
        "path": "/v2/radar/970a0439d4b8"
      },
      {
        "time": 1775856000,
        "path": "/v2/radar/ef993549b67a"
      }
    ],
    "nowcast": []
  },
  "satellite": {
    "infrared": []
  }
}