{
  "generated": 1777617924,
  "host": "https://tilecache.rainviewer.com",
  "radar": {
    "past": [
      {
        "time": 1777610400,
        "path": "/v2/radar/2bf2e81a9981"
      },
      {
        "time": 1777611000,
        "path": "/v2/radar/97fac6ba6c38"
      },
      {
        "time": 1777611600,
        "path": "/v2/radar/ffceb80ee8b9"
      },
      {
        "time": 1777612200,
        "path": "/v2/radar/4f8ce8b3d8bb"
      },
      {
        "time": 1777612800,
        "path": "/v2/radar/3fe98b0bfd60"
      },
      {
        "time": 1777613400,
        "path": "/v2/radar/f5ca147c7236"
      },
      {
        "time": 1777614000,
        "path": "/v2/radar/358f12dfb89c"
      },
      {
        "time": 1777614600,
        "path": "/v2/radar/f5700d2d733d"
      },
      {
        "time": 1777615200,
        "path": "/v2/radar/7d8ba7525db5"
      },
      {
        "time": 1777615800,
        "path": "/v2/radar/a15f275d3785"
      },
      {
        "time": 1777616400,
        "path": "/v2/radar/45a85fe3f798"
      },
      {
        "time": 1777617000,
        "path": "/v2/radar/8931600d6916"
      },
      {
        "time": 1777617600,
        "path": "/v2/radar/30dc75a9ca7b"
      }
    ],
    "nowcast": []
  },
  "satellite": {
    "infrared": []
  }
}