{
  "generated": 1775289672,
  "host": "https://tilecache.rainviewer.com",
  "radar": {
    "past": [
      {
        "time": 1775282400,
        "path": "/v2/radar/b3b59cbfeb9d"
      },
      {
        "time": 1775283000,
        "path": "/v2/radar/a70641a1f796"
      },
      {
        "time": 1775283600,
        "path": "/v2/radar/1638ebc16a91"
      },
      {
        "time": 1775284200,
        "path": "/v2/radar/b1805c271022"
      },
      {
        "time": 1775284800,
        "path": "/v2/radar/08a97af055f8"
      },
      {
        "time": 1775285400,
        "path": "/v2/radar/36a0941d76d0"
      },
      {
        "time": 1775286000,
        "path": "/v2/radar/a03fa6c9d02f"
      },
      {
        "time": 1775286600,
        "path": "/v2/radar/8c538eebdd05"
      },
      {
        "time": 1775287200,
        "path": "/v2/radar/fef7a024f754"
      },
      {
        "time": 1775287800,
        "path": "/v2/radar/c5cf0306dba0"
      },
      {
        "time": 1775288400,
        "path": "/v2/radar/3b64c587fa7c"
      },
      {
        "time": 1775289000,
        "path": "/v2/radar/338e9ff24fab"
      },
      {
        "time": 1775289600,
        "path": "/v2/radar/4f417f27cbe2"
      }
    ],
    "nowcast": []
  },
  "satellite": {
    "infrared": []
  }
}