{
  "generated_at": "2026-04-01T15:54:31Z",
  "radar": {
    "past": [
      {
        "time": 1775051400,
        "path": "/v2/radar/c9a82e378e77"
      },
      {
        "time": 1775052000,
        "path": "/v2/radar/89bbdc9d7f53"
      },
      {
        "time": 1775052600,
        "path": "/v2/radar/6c90039659a5"
      },
      {
        "time": 1775053200,
        "path": "/v2/radar/0f8bb66b9bd2"
      },
      {
        "time": 1775053800,
        "path": "/v2/radar/3f390a04fa97"
      },
      {
        "time": 1775054400,
        "path": "/v2/radar/65bf1b2dffcb"
      },
      {
        "time": 1775055000,
        "path": "/v2/radar/32a0516cd7a4"
      },
      {
        "time": 1775055600,
        "path": "/v2/radar/fca228745530"
      },
      {
        "time": 1775056200,
        "path": "/v2/radar/18164a2e2f7f"
      },
      {
        "time": 1775056800,
        "path": "/v2/radar/ce6c70ae2cf2"
      },
      {
        "time": 1775057400,
        "path": "/v2/radar/38a5fe9c4d79"
      },
      {
        "time": 1775058000,
        "path": "/v2/radar/3a3b3e8907d3"
      },
      {
        "time": 1775058600,
        "path": "/v2/radar/d29488c56ad0"
      }
    ],
    "nowcast": []
  },
  "satellite": {
    "infrared": []
  },
  "tile_url_template": "https://tilecache.rainviewer.com/v2/radar/{path}/256/{z}/{x}/{y}/2/1_1.png",
  "sat_url_template": "https://tilecache.rainviewer.com/v2/satellite/infrared/{path}/256/{z}/{x}/{y}/0/0_0.png"
}