{
  "generated": 1776071333,
  "host": "https://tilecache.rainviewer.com",
  "radar": {
    "past": [
      {
        "time": 1776063600,
        "path": "/v2/radar/57ab78c035a1"
      },
      {
        "time": 1776064200,
        "path": "/v2/radar/829d44bd5bd9"
      },
      {
        "time": 1776064800,
        "path": "/v2/radar/92789dec5755"
      },
      {
        "time": 1776065400,
        "path": "/v2/radar/b35029108347"
      },
      {
        "time": 1776066000,
        "path": "/v2/radar/07f013c99c16"
      },
      {
        "time": 1776066600,
        "path": "/v2/radar/cda760bb640d"
      },
      {
        "time": 1776067200,
        "path": "/v2/radar/7be38c378f31"
      },
      {
        "time": 1776067800,
        "path": "/v2/radar/b880468e190d"
      },
      {
        "time": 1776068400,
        "path": "/v2/radar/f36a2eb316f1"
      },
      {
        "time": 1776069000,
        "path": "/v2/radar/6d6eb6a4ff15"
      },
      {
        "time": 1776069600,
        "path": "/v2/radar/b66096441999"
      },
      {
        "time": 1776070200,
        "path": "/v2/radar/487b9cecc615"
      },
      {
        "time": 1776070800,
        "path": "/v2/radar/7f55be97d005"
      }
    ],
    "nowcast": []
  },
  "satellite": {
    "infrared": []
  }
}