{
  "generated": 1776434856,
  "host": "https://tilecache.rainviewer.com",
  "radar": {
    "past": [
      {
        "time": 1776427200,
        "path": "/v2/radar/0c36c6b24bac"
      },
      {
        "time": 1776427800,
        "path": "/v2/radar/84bd217c233e"
      },
      {
        "time": 1776428400,
        "path": "/v2/radar/e01a6492706c"
      },
      {
        "time": 1776429000,
        "path": "/v2/radar/6569a6d2c931"
      },
      {
        "time": 1776429600,
        "path": "/v2/radar/d66bd15b794f"
      },
      {
        "time": 1776430200,
        "path": "/v2/radar/0a3deb20ecee"
      },
      {
        "time": 1776430800,
        "path": "/v2/radar/1fdf24993272"
      },
      {
        "time": 1776431400,
        "path": "/v2/radar/fe4751469e41"
      },
      {
        "time": 1776432000,
        "path": "/v2/radar/b63fcb1b9202"
      },
      {
        "time": 1776432600,
        "path": "/v2/radar/f5743b71bd95"
      },
      {
        "time": 1776433200,
        "path": "/v2/radar/b7a2c7e459d7"
      },
      {
        "time": 1776433800,
        "path": "/v2/radar/119bb634c98d"
      },
      {
        "time": 1776434400,
        "path": "/v2/radar/5cfc7aa5aa91"
      }
    ],
    "nowcast": []
  },
  "satellite": {
    "infrared": []
  }
}