{
  "generated_at": "2026-04-21T21:32:22Z",
  "radar": {
    "past": [
      {
        "time": 1776799800,
        "path": "/v2/radar/fd3d7638e381"
      },
      {
        "time": 1776800400,
        "path": "/v2/radar/af51277ee6df"
      },
      {
        "time": 1776801000,
        "path": "/v2/radar/be26c9a3ec8e"
      },
      {
        "time": 1776801600,
        "path": "/v2/radar/15de21937dde"
      },
      {
        "time": 1776802200,
        "path": "/v2/radar/6e05c98b74c3"
      },
      {
        "time": 1776802800,
        "path": "/v2/radar/b9f76d0542cf"
      },
      {
        "time": 1776803400,
        "path": "/v2/radar/b662e862de53"
      },
      {
        "time": 1776804000,
        "path": "/v2/radar/171e120b53eb"
      },
      {
        "time": 1776804600,
        "path": "/v2/radar/094cd823cb84"
      },
      {
        "time": 1776805200,
        "path": "/v2/radar/38460d71a034"
      },
      {
        "time": 1776805800,
        "path": "/v2/radar/2b56d96c5e5e"
      },
      {
        "time": 1776806400,
        "path": "/v2/radar/e4cfc857f4e2"
      },
      {
        "time": 1776807000,
        "path": "/v2/radar/eec186ed803a"
      }
    ],
    "nowcast": []
  },
  "satellite": {
    "infrared": []
  },
  "tile_url_template": "https://tilecache.rainviewer.com/v2/radar/{path}/256/{z}/{x}/{y}/2/1_1.png",
  "sat_url_template": "https://tilecache.rainviewer.com/v2/satellite/infrared/{path}/256/{z}/{x}/{y}/0/0_0.png"
}