{
  "generated_at": "2026-04-02T09:17:10Z",
  "radar": {
    "past": [
      {
        "time": 1775113800,
        "path": "/v2/radar/706b0742e461"
      },
      {
        "time": 1775114400,
        "path": "/v2/radar/72a703cf2c23"
      },
      {
        "time": 1775115000,
        "path": "/v2/radar/95425b7c805b"
      },
      {
        "time": 1775115600,
        "path": "/v2/radar/b0a66455e99b"
      },
      {
        "time": 1775116200,
        "path": "/v2/radar/d30e5e9c8c8b"
      },
      {
        "time": 1775116800,
        "path": "/v2/radar/03451805f205"
      },
      {
        "time": 1775117400,
        "path": "/v2/radar/2af72ebecf00"
      },
      {
        "time": 1775118000,
        "path": "/v2/radar/b7ffe3e5d1f6"
      },
      {
        "time": 1775118600,
        "path": "/v2/radar/1ccf836aaa72"
      },
      {
        "time": 1775119200,
        "path": "/v2/radar/b52c527aa6a8"
      },
      {
        "time": 1775119800,
        "path": "/v2/radar/ce66e6bd1d25"
      },
      {
        "time": 1775120400,
        "path": "/v2/radar/578f417d5507"
      },
      {
        "time": 1775121000,
        "path": "/v2/radar/d699b365ab59"
      }
    ],
    "nowcast": []
  },
  "satellite": {
    "infrared": []
  },
  "tile_url_template": "https://tilecache.rainviewer.com/v2/radar/{path}/256/{z}/{x}/{y}/2/1_1.png",
  "sat_url_template": "https://tilecache.rainviewer.com/v2/satellite/infrared/{path}/256/{z}/{x}/{y}/0/0_0.png"
}