{
  "generated_at": "2026-05-05T09:29:36Z",
  "radar": {
    "past": [
      {
        "time": 1777966200,
        "path": "/v2/radar/d34e458e45bb"
      },
      {
        "time": 1777966800,
        "path": "/v2/radar/08ace3411b1d"
      },
      {
        "time": 1777967400,
        "path": "/v2/radar/dee03dfc9761"
      },
      {
        "time": 1777968000,
        "path": "/v2/radar/16af867b12c6"
      },
      {
        "time": 1777968600,
        "path": "/v2/radar/efc83c565e84"
      },
      {
        "time": 1777969200,
        "path": "/v2/radar/6b7b1b459295"
      },
      {
        "time": 1777969800,
        "path": "/v2/radar/4abac6f33d8b"
      },
      {
        "time": 1777970400,
        "path": "/v2/radar/4fac2a9e3089"
      },
      {
        "time": 1777971000,
        "path": "/v2/radar/d1f02539fd3b"
      },
      {
        "time": 1777971600,
        "path": "/v2/radar/fb066671ff6b"
      },
      {
        "time": 1777972200,
        "path": "/v2/radar/1a2063852afe"
      },
      {
        "time": 1777972800,
        "path": "/v2/radar/78d287850f3e"
      },
      {
        "time": 1777973400,
        "path": "/v2/radar/0d812e0f3d62"
      }
    ],
    "nowcast": []
  },
  "satellite": {
    "infrared": []
  },
  "tile_url_template": "https://tilecache.rainviewer.com/v2/radar/{path}/256/{z}/{x}/{y}/2/1_1.png",
  "sat_url_template": "https://tilecache.rainviewer.com/v2/satellite/infrared/{path}/256/{z}/{x}/{y}/0/0_0.png"
}