{
  "generated": 1777276589,
  "host": "https://tilecache.rainviewer.com",
  "radar": {
    "past": [
      {
        "time": 1777269000,
        "path": "/v2/radar/4afe53b84e98"
      },
      {
        "time": 1777269600,
        "path": "/v2/radar/2da3e44f5b65"
      },
      {
        "time": 1777270200,
        "path": "/v2/radar/f2c1a9787527"
      },
      {
        "time": 1777270800,
        "path": "/v2/radar/85fdf1fab7b0"
      },
      {
        "time": 1777271400,
        "path": "/v2/radar/3adfd6e9f836"
      },
      {
        "time": 1777272000,
        "path": "/v2/radar/51c2e19517aa"
      },
      {
        "time": 1777272600,
        "path": "/v2/radar/1ecda798ba05"
      },
      {
        "time": 1777273200,
        "path": "/v2/radar/9f0eec2df22c"
      },
      {
        "time": 1777273800,
        "path": "/v2/radar/900f0bd60710"
      },
      {
        "time": 1777274400,
        "path": "/v2/radar/dfa3aa0da22e"
      },
      {
        "time": 1777275000,
        "path": "/v2/radar/5115dbb0fd20"
      },
      {
        "time": 1777275600,
        "path": "/v2/radar/2d2a926a66f3"
      },
      {
        "time": 1777276200,
        "path": "/v2/radar/59b280b3a04b"
      }
    ],
    "nowcast": []
  },
  "satellite": {
    "infrared": []
  }
}